[
    {
        "email":"vanderleiagxgalcoforado_mqoafsj@knowledgemd.com",
        "password":"ZCYCKnGBpwn"
    },
    {
        "email":"victoriazxialmeida_fjity@knowledgemd.com",
        "password":"hwfUUScES"
    },
    {
        "email":"yokoyscjardim_gomv@knowledgemd.com",
        "password":"ZtdvhuxYy"
    },
    {
        "email":"dionehdcmonteiro_zpjyxkx@knowledgemd.com",
        "password":"CtLiphWau"
    },
    {
        "email":"lavineasjyrojas_fumlwu@knowledgemd.com",
        "password":"wmMcHAvZD"
    },
    {
        "email":"modestappiesteves_ndmnq@knowledgemd.com",
        "password":"lfbutmmRQN"
    },
    {
        "email":"paulaonyvasconcelos_tfzyjbtn@knowledgemd.com",
        "password":"mpEfYPspGg"
    },
    {
        "email":"thaisoukcidreira_nqft@knowledgemd.com",
        "password":"GGLMjyrzGy"
    },
    {
        "email":"galenaorzabrantes_tptvzsw@knowledgemd.com",
        "password":"eGxBzfHGq"
    },
    {
    
        "password":"invalid"
    },
    {
        "email":"shiraewvgereissat_ftyddfxo@knowledgemd.com",
        "password":"YddcRArPXQe"
    }
    ]

    